aioquic/__init__.py
aioquic/_buffer.py
aioquic/_crypto.py
aioquic/buffer.py
aioquic/tls.py
aioquic/asyncio/__init__.py
aioquic/asyncio/client.py
aioquic/asyncio/protocol.py
aioquic/asyncio/server.py
aioquic/h0/__init__.py
aioquic/h0/connection.py
aioquic/h3/__init__.py
aioquic/h3/connection.py
aioquic/h3/events.py
aioquic/h3/exceptions.py
aioquic/quic/__init__.py
aioquic/quic/configuration.py
aioquic/quic/connection.py
aioquic/quic/crypto.py
aioquic/quic/events.py
aioquic/quic/logger.py
aioquic/quic/packet.py
aioquic/quic/packet_builder.py
aioquic/quic/rangeset.py
aioquic/quic/recovery.py
aioquic/quic/retry.py
aioquic/quic/stream.py
aioquic_mitmproxy-0.9.21.1.dist-info/LICENSE
aioquic_mitmproxy-0.9.21.1.dist-info/METADATA
aioquic_mitmproxy-0.9.21.1.dist-info/WHEEL
aioquic_mitmproxy-0.9.21.1.dist-info/top_level.txt
aioquic_mitmproxy-0.9.21.1.dist-info/RECORD
