Metadata-Version: 2.1
Name: aioquic_mitmproxy
Version: 0.9.21.1
Summary: Fork of aioquic (https://github.com/aiortc/aioquic) with adjustments for mitmproxy.
Author-email: Jeremy Lainé <jeremy.laine@m4x.org>, Manuel Meitinger <manuel@meitinger.at>
License: BSD-3-Clause
Project-URL: homepage, https://github.com/meitinger/aioquic_mitmproxy
Project-URL: documentation, https://aioquic.readthedocs.io/
Classifier: Development Status :: 4 - Beta
Classifier: Environment :: Web Environment
Classifier: Intended Audience :: Developers
Classifier: License :: OSI Approved :: BSD License
Classifier: Operating System :: OS Independent
Classifier: Programming Language :: Python
Classifier: Programming Language :: Python :: 3
Classifier: Programming Language :: Python :: 3.8
Classifier: Programming Language :: Python :: 3.9
Classifier: Programming Language :: Python :: 3.10
Classifier: Programming Language :: Python :: 3.11
Classifier: Topic :: Internet :: WWW/HTTP
Requires-Python: >=3.8
License-File: LICENSE
Requires-Dist: certifi
Requires-Dist: pylsqpack<0.4.0,>=0.3.3
Requires-Dist: pyopenssl>=22
Requires-Dist: service-identity>=23.1.0
Provides-Extra: dev
Requires-Dist: coverage[toml]>=7.2.2; extra == "dev"
